yagc/cli.py
yagc/git/branch_validator.py
yagc/github/repository_settings.py
yagc/tests/git/test_branch.py
yagc/tests/github/test_repository_settings.py
yagc-0.0.4.dist-info/entry_points.txt
yagc-0.0.4.dist-info/METADATA
yagc-0.0.4.dist-info/LICENSE
yagc-0.0.4.dist-info/WHEEL
yagc-0.0.4.dist-info/RECORD
