Metadata-Version: 2.1
Name: yagc
Version: 0.0.4
Summary: Yet Another Git Convention(s) - rules for working with text together
License: Apache-2
Author: Neon Law Foundation
Author-email: support@neonlaw.org
Requires-Python: >=3.9,<4.0
Classifier: License :: Other/Proprietary License
Classifier: Programming Language :: Python :: 3
Classifier: Programming Language :: Python :: 3.9
Classifier: Programming Language :: Python :: 3.10
Classifier: Programming Language :: Python :: 3.11
Requires-Dist: click (>=8.1.3,<9.0.0)
Requires-Dist: gitpython (>=3.1.29,<4.0.0)
Requires-Dist: pygithub (>=1.57,<2.0)
Requires-Dist: semver (==3.0.0-dev.4)
